gmic/__init__.cpython-38-aarch64-linux-gnu.so
gmic/__init__.pyi
gmic/py.typed
gmic.libs/libfftw3-34927772.so.3.5.8
gmic.libs/libfftw3_threads-2bf2c586.so.3.5.8
gmic.libs/libjbig-759d3fc1.so.2.1
gmic.libs/libjpeg-ad9d4d2a.so.62.3.0
gmic.libs/libpng16-92e2b0a1.so.16.37.0
gmic.libs/libtiff-eec6f550.so.5.8.0
gmic.libs/libwebp-f6b0c2e8.so.7.1.1
gmic.libs/libzstd-53ea8407.so.1.5.5
gmic-3.6.3.post1.dist-info/METADATA
gmic-3.6.3.post1.dist-info/WHEEL
gmic-3.6.3.post1.dist-info/RECORD
gmic-3.6.3.post1.dist-info/licenses/COPYING
gmic-3.6.3.post1.dist-info/sboms/auditwheel.cdx.json
