Metadata-Version: 2.1
Name: gmic
Version: 3.6.3.post1
Summary: Python bindings for the G'MIC C++ image processing library
Keywords: gmic,graphics,image,filter
Author-Email: =?utf-8?q?David_Tschumperl=C3=A9?= <David.Tschumperle@ensicaen.fr>, =?utf-8?q?S=C3=A9bastien_Fourey?= <Sebastien.Fourey@ensicaen.fr>, =?utf-8?q?Jonathan-David_Schr=C3=B6der?= <jonathan.schroder@gmail.com>, =?utf-8?q?Laur=C3=A9line_Nevin?= <laureline.nevin@unicaen.fr>
Classifier: Development Status :: 4 - Beta
Classifier: Intended Audience :: Developers
Classifier: Intended Audience :: Education
Classifier: Intended Audience :: Healthcare Industry
Classifier: Intended Audience :: Other Audience
Classifier: Intended Audience :: End Users/Desktop
Classifier: Topic :: Artistic Software
Classifier: Topic :: Scientific/Engineering :: Image Processing
Classifier: Topic :: Software Development
Classifier: Topic :: Multimedia :: Graphics
Classifier: License :: OSI Approved :: CEA CNRS Inria Logiciel Libre License, version 2.1 (CeCILL-2.1)
Classifier: Programming Language :: Python :: 3
Project-URL: Homepage, https://gmic.eu/
Project-URL: source, https://github.com/GreycLab/gmic-py
Project-URL: releasenotes, https://github.com/GreycLab/gmic-py/releases/
Project-URL: issues, https://github.com/GreycLab/gmic-py/issues
Project-URL: funding, https://libreart.info/en/projects/gmic
Project-URL: Say Thanks!, https://twitter.com/gmic_eu
Requires-Python: >=3.8
